openfoam_residuals/__init__.py
openfoam_residuals/filesystem.py
openfoam_residuals/main.py
openfoam_residuals/plot.py
openfoam_residuals-0.1.0.dist-info/METADATA
openfoam_residuals-0.1.0.dist-info/WHEEL
openfoam_residuals-0.1.0.dist-info/licenses/LICENSE
openfoam_residuals-0.1.0.dist-info/RECORD
