Metadata-Version: 2.4
Name: openfoam-residuals
Version: 0.1.0
Summary: A Python interface to parse and plot OpenFOAM residuals
Project-URL: Homepage, https://github.com/Eddy3D-Dev/OpenFOAM-Residuals/
Project-URL: Repository, https://github.com/Eddy3D-Dev/OpenFOAM-Residuals/
Project-URL: Documentation, https://github.com/Eddy3D-Dev/OpenFOAM-Residuals/
Author-email: Patrick Kastner <patrick.kastner@gmail.com>
License-File: LICENSE
Classifier: Development Status :: 4 - Beta
Classifier: Framework :: AsyncIO
Classifier: Intended Audience :: Developers
Classifier: Intended Audience :: Science/Research
Classifier: License :: OSI Approved :: GNU General Public License v3 (GPLv3)
Classifier: Operating System :: POSIX
Classifier: Programming Language :: Python :: 3 :: Only
Classifier: Programming Language :: Python :: 3.8
Classifier: Programming Language :: Python :: 3.9
Classifier: Programming Language :: Python :: 3.10
Classifier: Programming Language :: Python :: 3.11
Classifier: Programming Language :: Python :: 3.12
Classifier: Programming Language :: Python :: 3.13
Classifier: Topic :: Scientific/Engineering
Classifier: Topic :: Software Development
Classifier: Typing :: Typed
Requires-Python: >=3.8
Requires-Dist: matplotlib>=3
Requires-Dist: numpy<3,>=1
Requires-Dist: pandas<3,>=2
Requires-Dist: typing-extensions<5,>=4; python_version < '3.14'
Provides-Extra: docs
Requires-Dist: ruff; extra == 'docs'
